config_path/__init__.py
config_path-1.0.5.dist-info/LICENSE
config_path-1.0.5.dist-info/METADATA
config_path-1.0.5.dist-info/WHEEL
config_path-1.0.5.dist-info/top_level.txt
config_path-1.0.5.dist-info/RECORD
