Metadata-Version: 2.1
Name: config-path
Version: 1.0.5
Summary: config_path is a library to work with paths to config folders and files in an OS independent way
Author-email: Barry Scott <barry@barrys-emacs.org>
License: Apache-2.0
Project-URL: Homepage, https://github.com/barry-scott/config-path
Project-URL: Bug Tracker, https://github.com/barry-scott/config-path/issues
Keywords: development
Classifier: Intended Audience :: End Users/Desktop
Classifier: Topic :: Utilities
Classifier: Environment :: Console
Classifier: Programming Language :: Python :: 3
Requires-Python: >=3.10
License-File: LICENSE
